System/UART_RX/Deserializer.sv
module Deserializer (

	input		wire				CLK,
	input		wire				RST,	
  input		wire				sampled_bit,
	input		wire				deser_en,
	input		wire	[3:0]	prescale,
	input		wire	[3:0]	edge_cnt,
	output	reg 	[7:0] P_DATA //assumed data bits is only 8 bits (no configurations)
);

always @(posedge CLK or negedge RST) 
	begin
		if (!RST) 
			begin
				P_DATA <= 8'b0;	
			end
		else if (deser_en && edge_cnt == (prescale - 4'b1))
			begin
				//TX sends LSB first so Shift right to recieive correctly
				P_DATA <= {sampled_bit,P_DATA[7:1]};
			end
	end

endmodule

System/UART_RX/stop_check.sv
module stop_check (

	input		wire	CLK,
	input		wire	RST,
  input		wire 	stp_chk_en,
	input		wire	sampled_bit,
	output	reg		stp_err
);

always @(posedge CLK or negedge RST ) 
	begin
		if (!RST) 
			begin
				stp_err <= 1'b0;	
			end	
		else if (stp_chk_en) 
			begin 
				//'1' if the stop bit isn't '1' as it should be 
				stp_err <= sampled_bit ^ 1'b1;
			end
		else
			begin
				stp_err <= 1'b0;
			end
	end

endmodule

System/UART_RX/parity_check.sv
module parity_check (

	input		wire				CLK,
	input		wire				RST,	
	input		wire				par_chk_en,
	input		wire				PAR_TYP,
	input		wire 				sampled_bit,
	input		wire	[7:0] P_DATA, //assumed data bits is only 8 bits (no configurations)
	output	reg					par_err
);

reg	parity_calc;

always @(*) 
	begin
		if (PAR_TYP) 
			begin
				parity_calc = ~^P_DATA;	
			end
		else
			begin
				parity_calc = ^P_DATA;
			end
	end

always @(posedge CLK or negedge RST) 
	begin
		if (!RST) 
			begin
				par_err <= 1'b0;	
			end	
		else if (par_chk_en)
			begin
				par_err <= parity_calc ^ sampled_bit;
			end
		else
			begin
				par_err <= 1'b0;	
			end
	end
	
endmodule

System/UART_RX/start_check.sv
module start_check (

	input		wire	CLK,
	input		wire	RST,
  input		wire 	strt_chk_en,
	input		wire	sampled_bit,
	output	reg		strt_glitch
);

always @(posedge CLK or negedge RST ) 
	begin
		if (!RST) 
			begin
				strt_glitch <= 1'b0;
			end	
		else if (strt_chk_en)
			begin
				//'1' if the start bit isn't '0' as it should be
				strt_glitch <= sampled_bit; 
			end
		else
			begin
				strt_glitch <= 1'b0;
			end
	end

endmodule

System/UART_RX/edge_bit_counter.sv
module edge_bit_counter (

	input 	wire 				CLK,
	input		wire				RST,
	input		wire				edge_en,
	input		wire	[3:0]	prescale,
	output	reg		[3:0]	bit_cnt,
	output 	reg		[3:0]	edge_cnt
);

// Internal Signal 
reg	edge_counter_done;

always @(*) 
	begin
		if(edge_cnt == (prescale - 4'b1))
			begin
				edge_counter_done = 1'b1;
			end		
		else
			begin
				edge_counter_done = 1'b0;
			end
	end

//edge counter 
always @(posedge CLK or negedge RST)
 	begin
 	 if(!RST)
 	  	begin
 	  		edge_cnt <= 4'b0 ;
				bit_cnt <= 4'b0;
 	  	end
 	 else if(edge_en)
 	  	begin
 	   	if (edge_counter_done)
		 			begin
 	  			  edge_cnt <= 4'b0 ;
						bit_cnt <= bit_cnt + 4'b1;
		 			end
				else
		 			begin
 	  			  edge_cnt <= edge_cnt + 4'b1 ;
		 			end	
 	  	end 
 	 else
 	  begin
 	   	edge_cnt <= 4'b0 ;
		bit_cnt <= 4'b0;
 	  end   
 	end
 
endmodule

System/UART_RX/Data_Sampling.sv
module Data_Sampling (

 input   	wire        		CLK,
 input   	wire        		RST,
 input   	wire        		RX_IN,
 input   	wire   [3:0]		prescale,
 input   	wire   [3:0]		edge_cnt,
 input   	wire        		dat_samp_en, 
 output  	reg         		sampled_bit	
// output		reg							sampled_bit_d
);

              
reg  [2:0]    Samples ;

wire [4:0]    half_edges ,
              edge_after_half ,
			  			edge_before_half ;

/*	Divide by 2 (shift right) the minus 1 because I start 
		counting from edge zero not one*/ 
assign 	half_edges    = (prescale >> 1) - 'b1 ;
assign 	half_edges_p1 =  half_edges + 'b1 ;
assign 	half_edges_n1 =  half_edges - 'b1 ;

// this block is for delayed sample bit for the parity check only
//always @(posedge CLK or negedge RST)
//	begin
//		if (!RST) 
//			begin
//				sampled_bit_d <= 1'b0;	
//			end
//		else if (edge_cnt == (prescale - 1))
//			begin
//				sampled_bit_d <= sampled_bit;
//			end
//	end

always @ (posedge CLK or negedge RST)
 	begin
 	 	if(!RST)
 	 	 	begin
 	 	 	 Samples <= 3'b0 ;
 	 	 	end
 	 	else 
 	 	 	begin
 	 	 	 	if(dat_samp_en) 
					begin
						if(edge_cnt == half_edges_n1)
 	 	 	 	  	 	begin
 	 	 	 	  	 	 Samples[0] <= RX_IN ;
 	 	 	 	  	 	end	
 	 	 	 	  	else if(edge_cnt == half_edges)
 	 	 	 	  	 	begin
 	 	 	 	  	 	 Samples[1] <= RX_IN ;
 	 	 	 	  	 	end	
 	 	 	 	  	else if(edge_cnt == half_edges_p1)
 	 	 	 	  	 	begin
 	 	 	 	  	 	 Samples[2] <= RX_IN ;
 	 	 	 	  	 	end
 	 	 	 		end
 	 	 		else
 	 	 	 	 	begin
 	 	 	 	 	 	Samples <= 3'b0 ;
 	 	 	 	 	end 
 	 	 	end	 
 	end
 

always @ (posedge CLK or negedge RST)
 	begin
 	 	if(!RST)
 	 	 	begin
 	 	 	 	sampled_bit <= 1'b0 ;
 	 	 	end
 	 	else
 	  	begin
 	  	 	if(dat_samp_en) 
			 		begin
 	  	   		case (Samples)
 	  	   		3'b000 : begin
 	  	   		          sampled_bit <= 1'b0 ;
 	  	   		         end	
 	  	   		3'b001 : begin
 	  	   		          sampled_bit <= 1'b0 ;
 	  	   		         end
 	  	   		3'b010 : begin
 	  	   		          sampled_bit <= 1'b0 ;
 	  	   		         end	
 	  	   		3'b011 : begin
 	  	   		          sampled_bit <= 1'b1 ;
 	  	   		         end	
 	  	   		3'b100 : begin
 	  	   		          sampled_bit <= 1'b0 ;
 	  	   		         end
 	  	   		3'b101 : begin
 	  	   		          sampled_bit <= 1'b1 ;
 	  	   		         end	
 	  	   		3'b110 : begin
 	  	   		          sampled_bit <= 1'b1 ;
 	  	   		         end
 	  	   		3'b111 : begin
 	  	   		          sampled_bit <= 1'b1 ;
 	  	   		         end
 	  	   		endcase
 	  	  	end
 	  	 	else
 	  	  	begin
 	  	  		sampled_bit <= 1'b0 ;
 	  	  	end	 
 	  	end
 	end 


endmodule

System/UART_RX/FSM_RX.sv
module FSM_RX (
	//assumed data bits is only 8 bits (no configurations)
	input		wire 				CLK,
	input		wire 				RST,
	input		wire				RX_IN,
	input		wire				PAR_EN,
	input		wire	[3:0]	prescale,	
	input		wire	[3:0]	edge_cnt,	//max no. of edges is 32 (prescale)
  input		wire	[3:0]	bit_cnt,  //max no. of bits in frame is 11 bits
	input		wire				par_err,
	input		wire				strt_glitch,
	input		wire				stp_err,
	output	reg 				data_valid,
	output	reg 				edge_en,
	output 	reg 				dat_samp_en,
	output 	reg 				par_chk_en,
	output 	reg 				strt_chk_en,
	output 	reg 				stp_chk_en,
	output	reg 				deser_en

);

// Gray Code Encoding
typedef enum bit [2:0] {
		IDLE		= 3'b000,
    START 	= 3'b001,
		DATA 		= 3'b011,
		PARITY	= 3'b010,
		STOP		= 3'b110,
		ERR_CHECK	= 3'b100

}e_state;

e_state current_state , next_state;
// State Transition Logic
always @(posedge CLK or negedge RST) 
	begin
		if (!RST) 
			begin
				current_state <= IDLE;	
			end
		else
			begin
				current_state <= next_state; 
			end
	end

reg		[3:0]		chk_edge;
reg		[3:0]		chk_edge_err;
// to determine the number of edges by knowing prescale
always @(*) 
	begin
		chk_edge = prescale - 4'd1;
		chk_edge_err = 4'd2;
	end

// Next State Logic
always @(*) 
	begin
		case (current_state)
			IDLE: begin  
							if (!RX_IN) //start receiving when first bit is zero(start bit)  
								begin
									next_state = START;
								end
							else
								begin
									next_state = IDLE;
								end
						end 

			START: begin  
							if (bit_cnt == 4'd0 && edge_cnt == chk_edge) 
								begin
									if (!strt_glitch) 
										begin
											next_state = DATA;
										end
									else
										begin
											next_state = IDLE;
										end
								end
							else
								begin
									next_state = START;
								end
						end

			DATA: begin  
							if (bit_cnt == 4'd8 && edge_cnt == chk_edge) 
								begin
									if (PAR_EN) 
										begin
											next_state = PARITY;
										end
									else
										begin
											next_state = STOP;
										end
								end
							else
								begin
									next_state = DATA;
								end
						end

			PARITY: begin  
							if (bit_cnt == 4'd9 && edge_cnt == chk_edge) 
								begin
									next_state = STOP;	
								end
							else
								begin
									next_state = PARITY ;
								end
						end   

			STOP: begin  
							if (PAR_EN) 
								begin
									if (bit_cnt == 4'd10 && edge_cnt == chk_edge_err) 
										begin
											next_state = ERR_CHECK;
										end
									else
										begin
											next_state = STOP;
										end
								end
							else
								begin
									if (bit_cnt == 4'd9 && edge_cnt == chk_edge_err) 
										begin
											next_state = ERR_CHECK;
										end
									else
										begin
											next_state = STOP;
										end	
								end
						end

			ERR_CHECK: 	begin
										if (!RX_IN) 
											begin
												next_state = START;	
											end
										else	
											begin
												next_state = IDLE;	
											end
									end

			default: 	begin
									next_state = IDLE;
								end    
		endcase
	end

// Output Logic
always @(*) 
	begin
		// default values
		data_valid	= 1'b0;
		edge_en			= 1'b0;
		dat_samp_en	= 1'b0;
		par_chk_en	= 1'b0;
		strt_chk_en	= 1'b0;
		stp_chk_en	= 1'b0;
		deser_en		= 1'b0;

		case (current_state)
			IDLE:	begin
							if (!RX_IN) 
								begin
									data_valid	= 1'b0;
									edge_en			= 1'b1;
									dat_samp_en	= 1'b1;
									par_chk_en	= 1'b0;
									strt_chk_en	= 1'b1;
									stp_chk_en	= 1'b0;
									deser_en		= 1'b0;
								end
							else
								begin
									data_valid	= 1'b0;
									edge_en			= 1'b0;
									dat_samp_en	= 1'b0;
									par_chk_en	= 1'b0;
									strt_chk_en	= 1'b0;
									stp_chk_en	= 1'b0;
									deser_en		= 1'b0;
								end
						end

			START:	begin
								data_valid	= 1'b0;
								edge_en			= 1'b1;
								dat_samp_en	= 1'b1;
								par_chk_en	= 1'b0;
								strt_chk_en	= 1'b1;
								stp_chk_en	= 1'b0;
								deser_en		= 1'b0;
							end 

			DATA:	begin
								data_valid	= 1'b0;
								edge_en			= 1'b1;
								dat_samp_en	= 1'b1;
								par_chk_en	= 1'b0;
								strt_chk_en	= 1'b0;
								stp_chk_en	= 1'b0;
								deser_en		= 1'b1;
							end 			

			PARITY:	begin
								data_valid	= 1'b0;
								edge_en			= 1'b1;
								dat_samp_en	= 1'b1;
								strt_chk_en	= 1'b0;
								stp_chk_en	= 1'b0;
								deser_en		= 1'b0;
								if (bit_cnt == 4'd9 && edge_cnt == chk_edge) 
								begin
									par_chk_en = 1'b1;	
								end
							end

			STOP:	begin
								data_valid	= 1'b0;
								edge_en			= 1'b1;
								dat_samp_en	= 1'b1;
								par_chk_en	= 1'b0;
								strt_chk_en	= 1'b0;
								stp_chk_en	= 1'b1;
								deser_en		= 1'b0;
							end 

			ERR_CHECK:	begin
										edge_en			= 1'b0;
										dat_samp_en	= 1'b0;
										par_chk_en	= 1'b0;
										strt_chk_en	= 1'b0;
										stp_chk_en	= 1'b0;
										deser_en		= 1'b0;
										if ((!par_err) && (!stp_err)) 
											begin
												data_valid = 1'b1;	
											end
										else
											begin
												data_valid = 1'b0;
											end
									end  
			
			default:	begin
									data_valid	= 1'b0;
									edge_en			= 1'b0;
									dat_samp_en	= 1'b0;
									par_chk_en	= 1'b0;
									strt_chk_en	= 1'b0;
									stp_chk_en	= 1'b0;
									deser_en		= 1'b0;							
								end
		endcase
	end

endmodule

System/UART_RX/UART_RX.sv
module UART_RX (

	input		wire 				CLK,
	input		wire				RST,
	input		wire				RX_IN,
	input		wire	[3:0]	prescale,
	input		wire				PAR_EN,
	input		wire				PAR_TYP,
	output 	reg		[7:0]	P_DATA,
	output 	reg					par_err,
	output	reg					stp_err,
	output	reg					data_valid
    
);

//Internal Wires
wire	[3:0]	edge_cnt;
wire	[3:0]	bit_cnt;
wire				strt_glitch;
wire				edge_en;
wire				dat_samp_en;
wire				par_chk_en;
wire				strt_chk_en;
wire				stp_chk_en;
wire				deser_en;
wire				sampled_bit;
//wire				sampled_bit_d;

FSM_RX U_FSM_RX (

	.CLK(CLK),
	.RST(RST),
	.RX_IN(RX_IN),
	.PAR_EN(PAR_EN),
	.prescale(prescale),
	.edge_cnt(edge_cnt),
	.bit_cnt(bit_cnt),
	.par_err(par_err),
	.strt_glitch(strt_glitch),
	.stp_err(stp_err),
	.data_valid(data_valid),
	.edge_en(edge_en),	
	.dat_samp_en(dat_samp_en),
	.par_chk_en(par_chk_en),
	.strt_chk_en(strt_chk_en),
	.stp_chk_en(stp_chk_en),
	.deser_en(deser_en)
);

Data_Sampling U_Data_Sampling (

	.CLK(CLK),
	.RST(RST),
	.RX_IN(RX_IN),
	.prescale(prescale),
	.edge_cnt(edge_cnt),
	.dat_samp_en(dat_samp_en),
	.sampled_bit(sampled_bit)
	//.sampled_bit_d(sampled_bit_d)
);

edge_bit_counter U_edge_bit_counter (

	.CLK(CLK),
	.RST(RST),
	.edge_en(edge_en),
	.prescale(prescale),
	.bit_cnt(bit_cnt),
	.edge_cnt(edge_cnt)
);

start_check U_start_check (

	.CLK(CLK),
	.RST(RST),
	.strt_chk_en(strt_chk_en),
	.sampled_bit(sampled_bit),
	.strt_glitch(strt_glitch)
);

parity_check U_parity_check (

	.CLK(CLK),
	.RST(RST),
	.par_chk_en(par_chk_en),
	.PAR_TYP(PAR_TYP),
	.sampled_bit(sampled_bit),
	.P_DATA(P_DATA),
	.par_err(par_err)	
);

stop_check U_stop_check (

	.CLK(CLK),
	.RST(RST),
	.stp_chk_en(stp_chk_en),
	.sampled_bit(sampled_bit),
	.stp_err(stp_err)
);

Deserializer U_Deserializer (

	.CLK(CLK),
	.RST(RST),
	.sampled_bit(sampled_bit),
	.deser_en(deser_en),
	.prescale(prescale),
	.edge_cnt(edge_cnt),
	.P_DATA(P_DATA)
);

endmodule

System/UART_RX/UART_RX_tb.sv
`timescale 1ns/1ps

module UART_RX_TB ();

// TX CLK = 115.2 KHz
localparam CLK_CYCLE_TX = 8.68 ;

reg 					CLK_TX_tb;
reg       		CLK_RX_tb;
reg						RST_tb;
reg						RX_IN_tb;
reg	    [3:0]	prescale_tb;
reg						PAR_EN_tb;
reg						PAR_TYP_tb;
wire		[7:0]	P_DATA_tb;
wire					par_err_tb;
wire					stp_err_tb;
wire					data_valid_tb;

// Initial block
initial 
  begin
	  	$dumpfile("UART_RX.vcd");
	  	$dumpvars;
		// Initial default values
	  	initialize();
		reset();	

		UART_CONFIG(1'b1,1'b0,4'd4);
		// data = 8'h17,prescale = 4,PAR_EN =1,EVEN_PAR
		receive_data(8'h16);
		check_received(8'h16);

		//@(2*CLK_CYCLE_TX);	
		#(4*CLK_CYCLE_TX);

		//UART_CONFIG(1'b1,1'b1,4'd4);
		// data = 8'h17,prescale = 4,PAR_EN =1,EVEN_PAR
		//receive_data(8'h16);
		//check_received(8'h16);
		//#(4*CLK_CYCLE_TX);
	
	  	// Apply reset at the end
	  	//reset();
	  	$stop;
	end

// TASKS
task initialize;
	begin
		CLK_TX_tb		= 1'b0;
		CLK_RX_tb		= 1'b0;
		RST_tb			= 1'b1;
		RX_IN_tb		= 1'b1; // UART IDLE
		prescale_tb	= 4'b1000; // prescale = 8
		PAR_EN_tb		= 1'b0;
		PAR_TYP_tb	= 1'b0;
	end
endtask

task reset;
	begin
		#(CLK_CYCLE_TX);
		RST_tb = 1'b0;
		#(CLK_CYCLE_TX);
		RST_tb = 1'b1;
		#(CLK_CYCLE_TX);		
	end
endtask

task UART_CONFIG ;
  input                   PAR_EN_tb_task ;
  input                   PAR_TYP_tb_task ;
  input    [3:0]          prescale_tb_task;

  begin
	PAR_EN_tb  		= PAR_EN_tb_task   ;
	PAR_TYP_tb    = PAR_TYP_tb_task  ;
	prescale_tb   = prescale_tb_task ;    	
  end
endtask

task receive_data ;
	input 	[7:0]	data_task;

	integer i;
	begin

		// Start Bit
		@(posedge CLK_TX_tb);
		RX_IN_tb <= 1'b0;

		for (i = 0;i < 8 ;i = i+1 ) 
			begin
				@(posedge CLK_TX_tb);
				RX_IN_tb <= data_task[i];	
			end
		
		if (PAR_EN_tb)
			begin
				@(posedge CLK_TX_tb);
				if (!PAR_TYP_tb) 
					begin
						RX_IN_tb <= ^data_task;
					end
				else
					begin
						RX_IN_tb <= ~^data_task;
					end
			end
		//Stop Bit

		@(posedge CLK_TX_tb);
		RX_IN_tb <= 1'b1;

		#CLK_TX_tb;
	end
endtask

task check_received (

	input 	[7:0]	exp_data_task
); 
	begin
		wait(data_valid_tb);
		if(P_DATA_tb == exp_data_task) 
			begin
				$display("Test Case succeeded");
			end
		else
			begin
				$display("Test Case failed");
			end
	end
endtask

/*  Clock Generators (CLK_RX_tb) multiply the frequency by prescale
    so divide the clk period of CLK_TX_tb by it*/
always #(CLK_CYCLE_TX/prescale_tb/2) CLK_RX_tb = ~CLK_RX_tb;
always #(CLK_CYCLE_TX/2) CLK_TX_tb = ~CLK_TX_tb;    

// DUT Instantiation
UART_RX DUT (

    .CLK(CLK_RX_tb),
    .RST(RST_tb),
    .RX_IN(RX_IN_tb),
    .prescale(prescale_tb),
    .PAR_EN(PAR_EN_tb),
    .PAR_TYP(PAR_TYP_tb),
    .P_DATA(P_DATA_tb),
    .par_err(par_err_tb),
    .stp_err(stp_err_tb),
    .data_valid(data_valid_tb)
);

endmodule

System/UART_RX/UART_RX.vcd
$date
	Sun Aug 31 18:33:09 2025
$end
$version
	QuestaSim Version 2021.1
$end
$timescale
	1ps
$end

$scope module UART_RX_TB $end
$var parameter 0 ! CLK_CYCLE_TX $end
$var reg 1 " CLK_TX_tb $end
$var reg 1 # CLK_RX_tb $end
$var reg 1 $ RST_tb $end
$var reg 1 % RX_IN_tb $end
$var reg 4 & prescale_tb [3:0] $end
$var reg 1 ' PAR_EN_tb $end
$var reg 1 ( PAR_TYP_tb $end
$var wire 1 ) P_DATA_tb [7] $end
$var wire 1 * P_DATA_tb [6] $end
$var wire 1 + P_DATA_tb [5] $end
$var wire 1 , P_DATA_tb [4] $end
$var wire 1 - P_DATA_tb [3] $end
$var wire 1 . P_DATA_tb [2] $end
$var wire 1 / P_DATA_tb [1] $end
$var wire 1 0 P_DATA_tb [0] $end
$var wire 1 1 par_err_tb $end
$var wire 1 2 stp_err_tb $end
$var wire 1 3 data_valid_tb $end

$scope task initialize $end
$upscope $end

$scope task reset $end
$upscope $end

$scope task UART_CONFIG $end
$var reg 1 4 PAR_EN_tb_task $end
$var reg 1 5 PAR_TYP_tb_task $end
$var reg 4 6 prescale_tb_task [3:0] $end
$upscope $end

$scope task receive_data $end
$var reg 8 7 data_task [7:0] $end
$var integer 32 8 i $end
$upscope $end

$scope task check_received $end
$var reg 8 9 exp_data_task [7:0] $end
$upscope $end

$scope module DUT $end
$var wire 1 : CLK $end
$var wire 1 ; RST $end
$var wire 1 < RX_IN $end
$var wire 1 = prescale [3] $end
$var wire 1 > prescale [2] $end
$var wire 1 ? prescale [1] $end
$var wire 1 @ prescale [0] $end
$var wire 1 A PAR_EN $end
$var wire 1 B PAR_TYP $end
$var reg 8 C P_DATA [7:0] $end
$var reg 1 D par_err $end
$var reg 1 E stp_err $end
$var reg 1 F data_valid $end
$var wire 1 G edge_cnt [3] $end
$var wire 1 H edge_cnt [2] $end
$var wire 1 I edge_cnt [1] $end
$var wire 1 J edge_cnt [0] $end
$var wire 1 K bit_cnt [3] $end
$var wire 1 L bit_cnt [2] $end
$var wire 1 M bit_cnt [1] $end
$var wire 1 N bit_cnt [0] $end
$var wire 1 O strt_glitch $end
$var wire 1 P edge_en $end
$var wire 1 Q dat_samp_en $end
$var wire 1 R par_chk_en $end
$var wire 1 S strt_chk_en $end
$var wire 1 T stp_chk_en $end
$var wire 1 U deser_en $end
$var wire 1 V sampled_bit $end

$scope module U_FSM_RX $end
$var wire 1 : CLK $end
$var wire 1 ; RST $end
$var wire 1 < RX_IN $end
$var wire 1 A PAR_EN $end
$var wire 1 = prescale [3] $end
$var wire 1 > prescale [2] $end
$var wire 1 ? prescale [1] $end
$var wire 1 @ prescale [0] $end
$var wire 1 G edge_cnt [3] $end
$var wire 1 H edge_cnt [2] $end
$var wire 1 I edge_cnt [1] $end
$var wire 1 J edge_cnt [0] $end
$var wire 1 K bit_cnt [3] $end
$var wire 1 L bit_cnt [2] $end
$var wire 1 M bit_cnt [1] $end
$var wire 1 N bit_cnt [0] $end
$var wire 1 W par_err $end
$var wire 1 O strt_glitch $end
$var wire 1 X stp_err $end
$var reg 1 Y data_valid $end
$var reg 1 Z edge_en $end
$var reg 1 [ dat_samp_en $end
$var reg 1 \ par_chk_en $end
$var reg 1 ] strt_chk_en $end
$var reg 1 ^ stp_chk_en $end
$var reg 1 _ deser_en $end
$var reg 3 ` current_state [2:0] $end
$var reg 3 a next_state [2:0] $end
$var reg 4 b chk_edge [3:0] $end
$var reg 4 c chk_edge_err [3:0] $end
$upscope $end

$scope module U_Data_Sampling $end
$var wire 1 : CLK $end
$var wire 1 ; RST $end
$var wire 1 < RX_IN $end
$var wire 1 = prescale [3] $end
$var wire 1 > prescale [2] $end
$var wire 1 ? prescale [1] $end
$var wire 1 @ prescale [0] $end
$var wire 1 G edge_cnt [3] $end
$var wire 1 H edge_cnt [2] $end
$var wire 1 I edge_cnt [1] $end
$var wire 1 J edge_cnt [0] $end
$var wire 1 Q dat_samp_en $end
$var reg 1 d sampled_bit $end
$var reg 3 e Samples [2:0] $end
$var wire 1 f half_edges [4] $end
$var wire 1 g half_edges [3] $end
$var wire 1 h half_edges [2] $end
$var wire 1 i half_edges [1] $end
$var wire 1 j half_edges [0] $end
$var wire 1 k edge_after_half [4] $end
$var wire 1 l edge_after_half [3] $end
$var wire 1 m edge_after_half [2] $end
$var wire 1 n edge_after_half [1] $end
$var wire 1 o edge_after_half [0] $end
$var wire 1 p edge_before_half [4] $end
$var wire 1 q edge_before_half [3] $end
$var wire 1 r edge_before_half [2] $end
$var wire 1 s edge_before_half [1] $end
$var wire 1 t edge_before_half [0] $end
$var wire 1 u half_edges_p1 $end
$var wire 1 v half_edges_n1 $end
$upscope $end

$scope module U_edge_bit_counter $end
$var wire 1 : CLK $end
$var wire 1 ; RST $end
$var wire 1 P edge_en $end
$var wire 1 = prescale [3] $end
$var wire 1 > prescale [2] $end
$var wire 1 ? prescale [1] $end
$var wire 1 @ prescale [0] $end
$var reg 4 w bit_cnt [3:0] $end
$var reg 4 x edge_cnt [3:0] $end
$var reg 1 y edge_counter_done $end
$upscope $end

$scope module U_start_check $end
$var wire 1 : CLK $end
$var wire 1 ; RST $end
$var wire 1 S strt_chk_en $end
$var wire 1 V sampled_bit $end
$var reg 1 z strt_glitch $end
$upscope $end

$scope module U_parity_check $end
$var wire 1 : CLK $end
$var wire 1 ; RST $end
$var wire 1 R par_chk_en $end
$var wire 1 B PAR_TYP $end
$var wire 1 V sampled_bit $end
$var wire 1 { P_DATA [7] $end
$var wire 1 | P_DATA [6] $end
$var wire 1 } P_DATA [5] $end
$var wire 1 ~ P_DATA [4] $end
$var wire 1 !! P_DATA [3] $end
$var wire 1 "! P_DATA [2] $end
$var wire 1 #! P_DATA [1] $end
$var wire 1 $! P_DATA [0] $end
$var reg 1 %! par_err $end
$var reg 1 &! parity_calc $end
$upscope $end

$scope module U_stop_check $end
$var wire 1 : CLK $end
$var wire 1 ; RST $end
$var wire 1 T stp_chk_en $end
$var wire 1 V sampled_bit $end
$var reg 1 '! stp_err $end
$upscope $end

$scope module U_Deserializer $end
$var wire 1 : CLK $end
$var wire 1 ; RST $end
$var wire 1 V sampled_bit $end
$var wire 1 U deser_en $end
$var wire 1 = prescale [3] $end
$var wire 1 > prescale [2] $end
$var wire 1 ? prescale [1] $end
$var wire 1 @ prescale [0] $end
$var wire 1 G edge_cnt [3] $end
$var wire 1 H edge_cnt [2] $end
$var wire 1 I edge_cnt [1] $end
$var wire 1 J edge_cnt [0] $end
$var reg 8 (! P_DATA [7:0] $end
$upscope $end
$upscope $end
$upscope $end

$scope begin std $end
$upscope $end
$enddefinitions $end
#0
$dumpvars
0"
0#
1$
1%
b1000 &
0'
0(
x4
x5
bx 6
bx 7
bx 9
bx C
xD
xE
0F
0Y
0Z
0[
0\
0]
0^
0_
b0 `
b0 a
b111 b
b10 c
xd
bx e
bx w
bx x
0y
xz
x%!
x&!
x'!
bx (!
r8.68 !
bx 8
x0
x/
x.
x-
x,
x+
x*
x)
x1
x2
03
xJ
xI
xH
xG
xN
xM
xL
xK
xO
0P
0Q
0R
0S
0T
0U
xV
1j
1i
0h
0g
0f
zo
zn
zm
zl
zk
zt
zs
zr
zq
zp
0u
0v
0B
0A
0@
0?
0>
1=
1<
1;
0:
x$!
x#!
x"!
x!!
x~
x}
x|
x{
xX
xW
$end
#543
1#
1:
b0 e
0d
b0 x
b0 w
0z
0%!
0'!
0E
0D
0V
02
01
0N
0M
0L
0K
0J
0I
0H
0G
0O
0X
0W
#1086
0#
0:
#1629
1#
1:
#2172
0#
0:
#2715
1#
1:
#3258
0#
0:
#3801
1#
1:
#4340
1"
#4344
0#
0:
#4887
1#
1:
#5430
0#
0:
#5973
1#
1:
#6516
0#
0:
#7059
1#
1:
#7602
0#
0:
#8145
1#
1:
#8680
0$
0"
0;
b0 (!
b0 C
00
0/
0.
0-
0,
0+
0*
0)
0$!
0#!
0"!
0!!
0~
0}
0|
0{
0&!
#8688
0#
0:
#9231
1#
1:
#9774
0#
0:
#10317
1#
1:
#10860
0#
0:
#11403
1#
1:
#11946
0#
0:
#12489
1#
1:
#13020
1"
#13032
0#
0:
#13575
1#
1:
#14118
0#
0:
#14661
1#
1:
#15204
0#
0:
#15747
1#
1:
#16290
0#
0:
#16833
1#
1:
#17360
1$
0"
1;
#17376
0#
0:
#17919
1#
1:
#18462
0#
0:
#19005
1#
1:
#19548
0#
0:
#20091
1#
1:
#20634
0#
0:
#21177
1#
1:
#21700
1"
#21720
0#
0:
#22263
1#
1:
#22806
0#
0:
#23349
1#
1:
#23892
0#
0:
#24435
1#
1:
#24978
0#
0:
#25521
1#
1:
#26040
14
05
b100 6
1'
b100 &
b10110 7
0"
1A
1>
0=
0i
b11 b
#26064
0#
0:
#27149
1#
1:
#28234
0#
0:
#29319
1#
1:
#30380
1"
b0 8
0%
0<
b1 a
1Z
1[
1]
1P
1Q
1S
#30404
0#
0:
#31489
1#
1:
b1 x
b1 `
1J
0Z
0[
0]
1Z
1[
1]
#32574
0#
0:
#33659
1#
1:
b10 x
0J
1I
0Z
0[
0]
1Z
1[
1]
#34720
0"
#34744
0#
0:
#35829
1#
1:
b11 x
1J
b11 a
0Z
0[
0]
1Z
1[
1]
1y
#36914
0#
0:
#37999
1#
1:
b11 `
b0 x
b1 w
1N
0J
0I
0y
0Z
0[
0]
1Z
1[
1_
0S
1U
#39060
1"
b1 8
#39084
0#
0:
#40169
1#
1:
b1 x
1J
0Z
0[
0_
1Z
1[
1_
#41254
0#
0:
#42339
1#
1:
b10 x
0J
1I
0Z
0[
0_
1Z
1[
1_
#43400
0"
#43424
0#
0:
#44509
1#
1:
b11 x
1J
0Z
0[
0_
1Z
1[
1_
1y
#45594
0#
0:
#46679
1#
1:
b0 x
b10 w
0N
1M
0J
0I
0Z
0[
0_
1Z
1[
1_
0y
#47740
1"
b10 8
1%
1<
0Z
0[
0_
1Z
1[
1_
#47764
0#
0:
#48849
1#
1:
b1 e
b1 x
1J
0Z
0[
0_
1Z
1[
1_
#49934
0#
0:
#51019
1#
1:
b10 x
b11 e
0J
1I
0Z
0[
0_
1Z
1[
1_
#52080
0"
#52104
0#
0:
#53189
1#
1:
1d
b11 x
1V
1J
0Z
0[
0_
1Z
1[
1_
1y
#54274
0#
0:
#55359
1#
1:
b10000000 (!
b0 x
b11 w
b10000000 C
1)
1{
1N
0J
0I
0Z
0[
0_
1Z
1[
1_
1&!
0y
#56420
1"
b11 8
#56444
0#
0:
#57529
1#
1:
b1 x
1J
0Z
0[
0_
1Z
1[
1_
#58614
0#
0:
#59699
1#
1:
b10 x
0J
1I
0Z
0[
0_
1Z
1[
1_
#60760
0"
#60784
0#
0:
#61869
1#
1:
b11 x
1J
0Z
0[
0_
1Z
1[
1_
1y
#62954
0#
0:
#64039
1#
1:
b11000000 (!
b0 x
b100 w
b11000000 C
1*
1|
0N
0M
1L
0J
0I
0Z
0[
0_
1Z
1[
1_
0&!
0y
#65100
1"
b100 8
0%
0<
0Z
0[
0_
1Z
1[
1_
#65124
0#
0:
#66209
1#
1:
b10 e
b1 x
1J
0Z
0[
0_
1Z
1[
1_
#67294
0#
0:
#68379
1#
1:
b10 x
b0 e
0d
0V
0J
1I
0Z
0[
0_
1Z
1[
1_
#69440
0"
#69464
0#
0:
#70549
1#
1:
b11 x
1J
0Z
0[
0_
1Z
1[
1_
1y
#71634
0#
0:
#72719
1#
1:
b1100000 (!
b0 x
b101 w
b1100000 C
1+
0)
1}
0{
1N
0J
0I
0Z
0[
0_
1Z
1[
1_
0y
#73780
1"
b101 8
1%
1<
0Z
0[
0_
1Z
1[
1_
#73804
0#
0:
#74889
1#
1:
b1 e
b1 x
1J
0Z
0[
0_
1Z
1[
1_
#75974
0#
0:
#77059
1#
1:
b10 x
b11 e
0J
1I
0Z
0[
0_
1Z
1[
1_
#78120
0"
#78144
0#
0:
#79229
1#
1:
1d
b11 x
1V
1J
0Z
0[
0_
1Z
1[
1_
1y
#80314
0#
0:
#81399
1#
1:
b10110000 (!
b0 x
b110 w
b10110000 C
1,
0*
1)
1~
0|
1{
0N
1M
0J
0I
0Z
0[
0_
1Z
1[
1_
1&!
0y
#82460
1"
b110 8
0%
0<
0Z
0[
0_
1Z
1[
1_
#82484
0#
0:
