Verilog/Session_5/Assignment/Ass_1/Door_controller.v
module Door_controller (

input wire CLK,
input wire RST,
input wire DN_Max,
input wire UP_Max,
input wire Activate,
output reg UP_M,
output reg DN_M

);

// States Encoding (Gray for less power)
localparam IDLE  = 2'b00,
		   MV_UP = 2'b01,
		   MV_DN = 2'b11;

reg [1:0] current_state,
		  next_state;

// state transition
always @(posedge CLK or negedge RST) 
 begin
	if (!RST)  // reset to IDLE state
	 begin 
		current_state <= IDLE;
	 end
	else 
	 begin
		current_state <= next_state;        
	 end
 end

// next state logic
always @(*)   
 begin
  case (current_state)
  IDLE : begin
		 if (!Activate) 
		  begin
			next_state = IDLE;
		  end
		 else if (Activate && DN_Max && !UP_Max)
		  begin 
			next_state = MV_UP; // Open door
		  end
		 else 
		  begin
			next_state = MV_DN; // Close door       
		  end
		 end

  MV_UP :begin
		 if (UP_Max) // Fully opened
		  begin
			next_state = IDLE;
		  end
		 else 
		  begin
			next_state = MV_UP; // Open door        
		  end
		 end

  MV_DN :begin
		 if (DN_Max) // Fully closed
		  begin
			next_state = IDLE;
		  end
		 else 
		  begin
			next_state = MV_DN; // Close door       
		  end
		 end 

  default: begin
			next_state = IDLE;
		   end 
  endcase
 end

// output logic (Output depend only on current state)
always @(*)   
 begin
 UP_M = 1'b0;
 DN_M = 1'b0;
  case (current_state)
  IDLE : begin
			UP_M = 1'b0;
			DN_M = 1'b0;
		 end 

  MV_UP :begin
			UP_M = 1'b1;
			DN_M = 1'b0;
		 end 

  MV_DN :begin
			UP_M = 1'b0;
			DN_M = 1'b1;
		 end 

  default: begin
			UP_M = 1'b0;
			DN_M = 1'b0;
		   end 
  endcase
 end

 endmodule

Verilog/Session_5/Assignment/Ass_1/Door_controller_tb.v
`timescale 1ns/1ps

module Door_controller_tb ();

// Inputs
reg CLK_tb;
reg RST_tb;
reg DN_Max_tb;
reg UP_Max_tb;
reg Activate_tb;

// Outputs
wire UP_M_tb;
wire DN_M_tb;

parameter CLK_Period = 20;

// Testbench logic
initial 
  begin
    $dumpfile("Door_controller.vcd");
    $dumpvars;

    initialzie();

    reset();

    open (); 

    // check door is opening
    check_output(1'b1,1'b0);

    close ();

    // check door is closing
    check_output(1'b0,1'b1);

    reset();

    $display("\n--- Testbench Completed ---\n");
    $stop;
  end

task initialzie;
  begin
    // Initial values
    CLK_tb = 0;
    RST_tb = 1;    
    DN_Max_tb = 1;  // Door initially fully closed
    UP_Max_tb = 0;
    Activate_tb = 0;
  end
endtask

task reset;
  begin
    RST_tb = 1'b1;
    #CLK_Period
    RST_tb = 1'b0;
    #CLK_Period
    RST_tb = 1'b1;
  end
endtask

task open;
  begin
    #(4*CLK_Period) // wait 80 ns 
    DN_Max_tb = 1;
    UP_Max_tb = 0;
    Activate_tb = 1;
  end
endtask

task close;
  begin
    #(4*CLK_Period) // wait 80 ns 
    DN_Max_tb = 0;
    UP_Max_tb = 1;
    Activate_tb = 1;    
  end
endtask

task check_output(
  
input reg Exp_UP_M, 
input reg Exp_DN_M
);

  begin
    if ((UP_M_tb == Exp_UP_M) && (DN_M_tb == Exp_DN_M)) 
      begin
        $display("Door is moving correct at Sim.time = %0t",$time);
      end
    else 
      begin
        $display("Door is moving wrong at Sim.time = %0t",$time);
      end
  end
endtask


// Clock generation: 50 MHz ---> 20 ns period
always#10 CLK_tb = ~CLK_tb;

// Instantiate the Door_controller
Door_controller DUT (
    .CLK(CLK_tb),
    .RST(RST_tb),
    .DN_Max(DN_Max_tb),
    .UP_Max(UP_Max_tb),
    .Activate(Activate_tb),
    .UP_M(UP_M_tb),
    .DN_M(DN_M_tb)
);

endmodule

Verilog/Session_5/Assignment/Ass_1/Door_controller.vcd
$date
	Mon Aug  4 15:18:21 2025
$end
$version
	QuestaSim Version 2021.1
$end
$timescale
	1ps
$end

$scope module Door_controller_tb $end
$var parameter 32 ! CLK_Period $end
$var reg 1 " CLK_tb $end
$var reg 1 # RST_tb $end
$var reg 1 $ DN_Max_tb $end
$var reg 1 % UP_Max_tb $end
$var reg 1 & Activate_tb $end
$var wire 1 ' UP_M_tb $end
$var wire 1 ( DN_M_tb $end

$scope task initialzie $end
$upscope $end

$scope task reset $end
$upscope $end

$scope task open $end
$upscope $end

$scope task close $end
$upscope $end

$scope task check_output $end
$var reg 1 ) Exp_UP_M $end
$var reg 1 * Exp_DN_M $end
$upscope $end

$scope module DUT $end
$var parameter 2 + IDLE $end
$var parameter 2 , MV_UP $end
$var parameter 2 - MV_DN $end
$var wire 1 . CLK $end
$var wire 1 / RST $end
$var wire 1 0 DN_Max $end
$var wire 1 1 UP_Max $end
$var wire 1 2 Activate $end
$var reg 1 3 UP_M $end
$var reg 1 4 DN_M $end
$var reg 2 5 current_state [1:0] $end
$var reg 2 6 next_state [1:0] $end
$upscope $end
$upscope $end
$enddefinitions $end
#0
$dumpvars
0"
1#
1$
0%
0&
x)
x*
x3
x4
bx 5
b0 6
b10100 !
b0 +
b1 ,
b11 -
x'
x(
02
01
10
1/
0.
$end
#10000
1"
1.
b0 5
03
04
0'
0(
#20000
0#
0"
0/
0.
#30000
1"
1.
#40000
1#
0"
1/
0.
#50000
1"
1.
#60000
0"
0.
#70000
1"
1.
#80000
0"
0.
#90000
1"
1.
#100000
0"
0.
#110000
1"
1.
#120000
1&
1)
0*
0"
12
0.
b1 6
#130000
1"
1.
b1 5
13
1'
#140000
0"
0.
#150000
1"
1.
#160000
0"
0.
#170000
1"
1.
#180000
0"
0.
#190000
1"
1.
#200000
0$
1%
0)
1*
0"
00
11
0.
b0 6
#210000
1"
1.
b0 5
b11 6
03
0'
#220000
0#
0"
0/
0.
#230000
1"
1.
#240000
1#
