Power/Assignment/ClkDiv.v

module ClkDiv #( 
  parameter DIV_RATIO = 8 
)
(
  input  wire                     i_ref_clk ,             
  input  wire                     i_rst ,                 
  input  wire                     i_clk_en,               
  input  wire [DIV_RATIO-1: 0]    i_div_ratio,           
  output wire                     o_div_clk               
);



reg  [DIV_RATIO-2 :0]   count ;
wire [DIV_RATIO-2 :0]   half_togg ;  
wire [DIV_RATIO-2 :0]   half_togg_p1 ;                                                                        
reg                     div_clk ;
reg                     odd_togg_flag ;               
wire                    is_one ;
wire                    is_zero;
wire                    clk_en;
wire                    is_odd;


always @(posedge i_ref_clk or negedge i_rst)               
  begin 
    if(!i_rst)
      begin
        count <= 0 ;
        div_clk <= 0 ;	
        odd_togg_flag <= 1 ;
      end
    else if(clk_en) 
      begin
        if(!is_odd && (count == half_togg))             
          begin
            count <= 0 ;                                        
            div_clk <= ~div_clk ;                               		
          end
        else if((is_odd && (count == half_togg) && odd_togg_flag ) || (is_odd && (count == half_togg_p1) && !odd_togg_flag ))  
          begin  
            count <= 0 ;                                       
            div_clk <= ~div_clk ;		                        
            odd_togg_flag <= ~odd_togg_flag ;                      
          end
        else
          begin
            count <= count + 1'b1 ;
          end
      end
  end


assign is_odd = i_div_ratio[0];
assign half_togg = ((i_div_ratio >> 1) - 1);
assign half_togg_p1 = (i_div_ratio >> 1);


// leeh msh sa7
// assign half_togg = (i_div_ratio >> 1);
// assign half_togg_p1 = i_div_ratio - half_togg; 
// It can be half_togg_p1 = half_togg + 1; 

// Corner Case
assign is_zero = ~|i_div_ratio ;                              
assign is_one  = (i_div_ratio == 1'b1) ;                       
assign clk_en = i_clk_en & !is_one & !is_zero;                 
assign o_div_clk = clk_en ? div_clk : i_ref_clk ;              

endmodule

Power/Assignment/ClkDiv_tb.v
//`timescale 1ns/1ps

module ClkDiv_tb ();

parameter DIV_RATIO_TB = 8;

reg													i_ref_clk_tb;
reg													i_rst_tb;
reg													i_clk_en_tb;
reg		[DIV_RATIO_TB-1 : 0]	i_div_ratio_tb;
wire												o_div_clk_tb;

initial
	begin
		$dumpfile("ClkDiv.vcd");
    $dumpvars;	

    // Reset Asserted
    i_rst_tb = 1'b0 ;
   	#200
   	i_rst_tb = 1'b1;

   	i_ref_clk_tb = 1'b0 ;
   	i_rst_tb = 1'b1 ;
   	i_clk_en_tb = 1'b1 ;
   	i_div_ratio_tb = 'd2 ;
   	#200
   	i_div_ratio_tb = 'd3;
   	#200
   	i_div_ratio_tb = 'd4;
   	#200
   	i_div_ratio_tb = 'd5;
   	#200
   	i_div_ratio_tb = 'd6;
   	#200
   	i_div_ratio_tb = 'd7;
   	#200
   	i_div_ratio_tb = 'd0; // corner case
   	#200
   	i_div_ratio_tb = 'd1;	// corner case 
 		#200

 		i_clk_en_tb = 0;

   	#200
   	$stop ;

	end

always #10 i_ref_clk_tb = ~i_ref_clk_tb;


ClkDiv #(.DIV_RATIO(DIV_RATIO_TB)) DUT 
(

	.i_ref_clk(i_ref_clk_tb),
	.i_rst(i_rst_tb),
	.i_clk_en(i_clk_en_tb),
	.i_div_ratio(i_div_ratio_tb),
	.o_div_clk(o_div_clk_tb)

);

endmodule

Power/Assignment/ClkDiv.vcd
$date
	Wed Sep  3 16:17:58 2025
$end
$version
	QuestaSim Version 2021.1
$end
$timescale
	1ns
$end

$scope module ClkDiv_tb $end
$var parameter 32 ! DIV_RATIO_TB $end
$var reg 1 " i_ref_clk_tb $end
$var reg 1 # i_rst_tb $end
$var reg 1 $ i_clk_en_tb $end
$var reg 8 % i_div_ratio_tb [7:0] $end
$var wire 1 & o_div_clk_tb $end

$scope module DUT $end
$var parameter 32 ' DIV_RATIO $end
$var wire 1 ( i_ref_clk $end
$var wire 1 ) i_rst $end
$var wire 1 * i_clk_en $end
$var wire 1 + i_div_ratio [7] $end
$var wire 1 , i_div_ratio [6] $end
$var wire 1 - i_div_ratio [5] $end
$var wire 1 . i_div_ratio [4] $end
$var wire 1 / i_div_ratio [3] $end
$var wire 1 0 i_div_ratio [2] $end
$var wire 1 1 i_div_ratio [1] $end
$var wire 1 2 i_div_ratio [0] $end
$var wire 1 & o_div_clk $end
$var reg 7 3 count [6:0] $end
$var wire 1 4 half_togg [6] $end
$var wire 1 5 half_togg [5] $end
$var wire 1 6 half_togg [4] $end
$var wire 1 7 half_togg [3] $end
$var wire 1 8 half_togg [2] $end
$var wire 1 9 half_togg [1] $end
$var wire 1 : half_togg [0] $end
$var wire 1 ; half_togg_p1 [6] $end
$var wire 1 < half_togg_p1 [5] $end
$var wire 1 = half_togg_p1 [4] $end
$var wire 1 > half_togg_p1 [3] $end
$var wire 1 ? half_togg_p1 [2] $end
$var wire 1 @ half_togg_p1 [1] $end
$var wire 1 A half_togg_p1 [0] $end
$var reg 1 B div_clk $end
$var reg 1 C odd_togg_flag $end
$var wire 1 D is_one $end
$var wire 1 E is_zero $end
$var wire 1 F clk_en $end
$var wire 1 G is_odd $end
$upscope $end
$upscope $end
$enddefinitions $end
#0
$dumpvars
x"
0#
x$
bx %
b0 3
0B
1C
b1000 !
b1000 '
x&
x:
x9
x8
x7
x6
x5
x4
xA
x@
x?
x>
x=
x<
x;
xD
xE
xF
xG
x2
x1
x0
x/
x.
x-
x,
x+
x*
0)
x(
$end
#200
1#
0"
1$
b10 %
1"
1*
02
11
00
0/
0.
0-
0,
0+
0E
0G
0D
0:
09
08
07
06
05
04
1A
0@
0?
0>
0=
0<
0;
1F
0&
1)
1(
1B
1&
#210
0"
0(
#220
1"
1(
0B
0&
#230
0"
0(
#240
1"
1(
1B
1&
#250
0"
0(
#260
1"
1(
0B
0&
#270
0"
0(
#280
1"
1(
1B
1&
#290
0"
0(
#300
1"
1(
0B
0&
#310
0"
0(
#320
1"
1(
1B
1&
#330
0"
0(
#340
1"
1(
0B
0&
#350
0"
0(
#360
1"
1(
1B
1&
#370
0"
0(
#380
1"
1(
0B
0&
#390
0"
0(
#400
b11 %
1"
12
1G
1(
1B
0C
1&
#410
0"
0(
#420
1"
1(
b1 3
#430
0"
0(
#440
1"
1(
b0 3
0B
1C
0&
#450
0"
0(
#460
1"
1(
1B
0C
1&
#470
0"
0(
#480
1"
1(
b1 3
#490
0"
0(
#500
1"
1(
b0 3
0B
1C
0&
#510
0"
0(
#520
1"
1(
1B
0C
1&
#530
0"
0(
#540
1"
1(
b1 3
#550
0"
0(
#560
1"
1(
b0 3
0B
1C
0&
#570
0"
0(
#580
1"
1(
1B
0C
1&
#590
0"
0(
#600
b100 %
1"
02
01
10
0G
1:
0A
1@
1(
b1 3
#610
0"
0(
#620
1"
1(
b0 3
0B
0&
#630
0"
0(
#640
1"
1(
b1 3
#650
0"
0(
#660
1"
1(
b0 3
1B
1&
#670
0"
0(
#680
1"
1(
b1 3
#690
0"
0(
#700
1"
1(
b0 3
0B
0&
#710
0"
0(
#720
1"
1(
b1 3
#730
0"
0(
#740
1"
1(
b0 3
1B
1&
#750
0"
0(
#760
1"
1(
b1 3
#770
0"
0(
#780
1"
1(
b0 3
0B
0&
#790
0"
0(
#800
b101 %
1"
12
1G
1(
b1 3
#810
0"
0(
#820
1"
1(
b10 3
#830
0"
0(
#840
1"
1(
b0 3
1B
1C
1&
#850
0"
0(
#860
1"
1(
b1 3
#870
0"
0(
#880
1"
1(
b0 3
0B
0C
0&
#890
0"
0(
#900
1"
1(
b1 3
#910
0"
0(
#920
1"
1(
b10 3
#930
0"
0(
#940
1"
1(
b0 3
1B
1C
1&
#950
0"
0(
#960
1"
1(
b1 3
#970
0"
0(
#980
1"
1(
b0 3
0B
0C
0&
#990
0"
0(
#1000
b110 %
1"
02
11
0G
0:
19
1A
1(
b1 3
#1010
0"
0(
#1020
1"
1(
b10 3
#1030
0"
0(
#1040
1"
1(
b0 3
1B
1&
#1050
0"
0(
#1060
1"
1(
b1 3
#1070
0"
0(
#1080
1"
1(
b10 3
#1090
0"
0(
#1100
1"
1(
b0 3
0B
0&
#1110
0"
0(
#1120
1"
1(
b1 3
#1130
0"
0(
#1140
1"
1(
b10 3
#1150
0"
0(
#1160
1"
1(
b0 3
1B
1&
#1170
0"
0(
#1180
1"
1(
b1 3
#1190
0"
0(
#1200
b111 %
1"
12
1G
1(
b10 3
#1210
0"
0(
#1220
1"
1(
b11 3
#1230
0"
0(
#1240
1"
1(
b0 3
0B
1C
0&
#1250
0"
0(
#1260
1"
1(
b1 3
#1270
0"
0(
#1280
1"
1(
b10 3
#1290
0"
0(
#1300
1"
1(
b0 3
1B
0C
1&
#1310
0"
0(
#1320
1"
1(
b1 3
#1330
0"
0(
#1340
1"
1(
b10 3
#1350
0"
0(
#1360
1"
1(
b11 3
#1370
0"
0(
#1380
1"
1(
b0 3
0B
1C
0&
#1390
0"
0(
#1400
b0 %
1"
02
01
00
1E
0G
0F
1:
18
17
16
15
14
0A
0@
1(
1&
#1410
0"
0(
0&
#1420
1"
1(
1&
#1430
0"
0(
0&
#1440
1"
1(
1&
#1450
0"
0(
0&
#1460
1"
1(
1&
#1470
0"
0(
0&
#1480
1"
1(
1&
#1490
0"
0(
0&
#1500
1"
1(
1&
#1510
0"
0(
0&
#1520
1"
1(
1&
#1530
0"
0(
0&
#1540
1"
1(
1&
#1550
0"
0(
0&
#1560
1"
1(
1&
#1570
0"
0(
0&
#1580
1"
1(
1&
#1590
0"
0(
0&
#1600
b1 %
1"
12
1G
0E
1F
1D
0F
1(
1&
