Verilog/Session_2/Assignment/Up_Down_Counter.v
module Up_Down_Counter (

input wire [4:0]     IN,
input wire           Load,
input wire           Up,
input wire		 	 Down,
input wire 		     CLK,

output reg [4:0]     Counter,
output wire 		 High,		
output wire 		 Low   );

reg [4:0] Counter_comb; //internal connection

always @(posedge CLK) 
	begin
		Counter <= Counter_comb;		
	end

always @(*) 
	begin
		if (Load) 
			begin
				Counter_comb = IN;	
			end
		else if (Down && !Low) 
			begin
				Counter_comb = Counter - 5'b00001;
			end
		else if (Up && !High && Down) // corrected (see explanation in notes) 
			begin
				Counter_comb = Counter + 5'b00001;
			end
		else 
			begin
				Counter_comb = Counter;	
			end

	end

assign High = (Counter == 5'b11111) ;
assign Low = (Counter == 5'b0);

endmodule

Verilog/Session_2/Assignment/Up_Down_Counter_tb.v
//time_unit = 1ns & time percision = 1ps
`timescale 1ns/1ps

module Up_Down_Counter_tb ();

reg [4:0] IN_tb;
reg       Load_tb;
reg		  Up_tb;
reg 	  Down_tb;
reg 	  CLK_tb;

wire [4:0] Counter_tb;
wire   	   High_tb;
wire	   Low_tb;	


initial 
	begin
		$dumpfile("Up_Down_Counter.vcd");
		$dumpvars;
		IN_tb = 5'b01101;
		Load_tb = 1'b0;
		Up_tb = 1'b0;
		Down_tb = 1'b0;
		CLK_tb = 1'b0;
		
		//wait for one clk cycle
		#10 
		$display("First Test Case"); // test load function
		Load_tb = 1'b1;
		#10
		if (Counter_tb == 5'b01101) 
			$display("First TEST CASE is Passed with counter value = %0h at simulation time",Counter_tb,$time);
		else 
			$display("First TEST CASE is Failed with counter value = %0h at simulation time",Counter_tb,$time);
		
		$display("Second Test Case"); // test load priority
		Load_tb = 1'b1;
		Down_tb = 1'b1;
		#10
		if (Counter_tb == 5'b01101) 
			$display("Second TEST CASE is Passed with counter value = %0h at simulation time",Counter_tb,$time);
		else 
			$display("Second TEST CASE is Failed with counter value = %0h at simulation time",Counter_tb,$time);

		$display("Third Test Case"); // test up function
		Load_tb = 1'b0;
		Down_tb = 1'b0;
		Up_tb = 1'b1;
		#10                          //wait for 1 clk cycles so counter has to go from 13 to 14(01110)
		if (Counter_tb == 5'b01110)
			$display("Third TEST CASE is Passed with counter value = %0h at simulation time",Counter_tb,$time);
		else 
			$display("Third TEST CASE is Failed with counter value = %0h at simulation time",Counter_tb,$time);		

		$display("Fourth Test Case"); // test down function
		Load_tb = 1'b0;
		Up_tb = 1'b0;
		Down_tb = 1'b1;
		#30                          //wait for 3 clk cycles so counter has to go back to 11 (01011)
		if (Counter_tb == 5'b01011)
			$display("Fourth TEST CASE is Passed with counter value = %0h at simulation time",Counter_tb,$time);
		else 
			$display("Fourth TEST CASE is Failed with counter value = %0h at simulation time",Counter_tb,$time);		

		$display("Fifth Test Case"); // test down priority
		Load_tb = 1'b0;
		Up_tb = 1'b1;
		Down_tb = 1'b1;
		#30                          //wait for 3 clk cycles so counter has to go from 11 to 8(01000)
		if (Counter_tb == 5'b01000)
			$display("Fifth TEST CASE is Passed with counter value = %0h at simulation time",Counter_tb,$time);
		else 
			$display("Fifth TEST CASE is Failed with counter value = %0h at simulation time",Counter_tb,$time);						

		$display("Sixth Test Case"); // test Down function (Low Flag test)
		Load_tb = 1'b0;
		Up_tb = 1'b0;
		Down_tb = 1'b1;
		#110                          //wait for 10 clk cycles so counter has to go from 10 to 0
		if (Counter_tb == 5'b0 && Low_tb == 1'b1)
			$display("Sixth TEST CASE is Passed with counter value = %0h at simulation time",Counter_tb,$time);
		else 
			$display("Sixth TEST CASE is Failed with counter value = %0h at simulation time",Counter_tb,$time);				
		#100
		$stop; //finish simulation
	end


// Clock generator
always#5	CLK_tb = ~CLK_tb;    // frequency = 100MHz

// Design instantiation
Up_Down_Counter DUt (

	.IN(IN_tb),
	.Load(Load_tb),
	.Up(Up_tb),
	.Down(Down_tb),
	.CLK(CLK_tb),
	.Counter(Counter_tb),
	.High(High_tb),
	.Low(Low_tb)
	);


endmodule

Verilog/Session_2/Assignment/Up_Down_Counter.vcd
$date
	Tue Jul 15 12:21:25 2025
$end
$version
	QuestaSim Version 2021.1
$end
$timescale
	1ps
$end

$scope module Up_Down_Counter_tb $end
$var reg 5 ! IN_tb [4:0] $end
$var reg 1 " Load_tb $end
$var reg 1 # Up_tb $end
$var reg 1 $ Down_tb $end
$var reg 1 % CLK_tb $end
$var wire 1 & Counter_tb [4] $end
$var wire 1 ' Counter_tb [3] $end
$var wire 1 ( Counter_tb [2] $end
$var wire 1 ) Counter_tb [1] $end
$var wire 1 * Counter_tb [0] $end
$var wire 1 + High_tb $end
$var wire 1 , Low_tb $end

$scope module DUt $end
$var wire 1 - IN [4] $end
$var wire 1 . IN [3] $end
$var wire 1 / IN [2] $end
$var wire 1 0 IN [1] $end
$var wire 1 1 IN [0] $end
$var wire 1 2 Load $end
$var wire 1 3 Up $end
$var wire 1 4 Down $end
$var wire 1 5 CLK $end
$var reg 5 6 Counter [4:0] $end
$var wire 1 + High $end
$var wire 1 , Low $end
$var reg 5 7 Counter_comb [4:0] $end
$upscope $end
$upscope $end
$enddefinitions $end
#0
$dumpvars
b1101 !
0"
0#
0$
0%
bx 6
bx 7
x*
x)
x(
x'
x&
x+
x,
05
04
03
02
11
00
1/
1.
0-
$end
#5000
1%
15
#10000
1"
0%
12
05
b1101 7
#15000
1%
15
b1101 6
1*
0)
1(
1'
0&
0,
0+
#20000
1$
0%
14
05
#25000
1%
15
#30000
0"
0$
1#
0%
02
04
13
05
b1110 7
#35000
1%
15
b1110 6
0*
1)
b1111 7
#40000
0#
1$
0%
03
14
05
b1101 7
#45000
1%
15
b1101 6
1*
0)
b1100 7
#50000
0%
05
#55000
1%
15
b1100 6
0*
b1011 7
#60000
0%
05
#65000
1%
15
b1011 6
1*
1)
0(
b1010 7
#70000
1#
0%
13
05
#75000
1%
15
b1010 6
0*
b1001 7
#80000
0%
05
#85000
1%
15
b1001 6
1*
0)
b1000 7
#90000
0%
05
#95000
1%
15
b1000 6
0*
b111 7
#100000
0#
0%
03
05
#105000
1%
15
b111 6
1*
1)
1(
0'
b110 7
#110000
0%
05
#115000
1%
15
b110 6
0*
b101 7
#120000
0%
05
#125000
1%
15
b101 6
1*
0)
b100 7
#130000
0%
05
#135000
1%
15
b100 6
0*
b11 7
#140000
0%
05
#145000
1%
15
b11 6
1*
1)
0(
b10 7
#150000
0%
05
#155000
1%
15
b10 6
0*
b1 7
#160000
0%
05
#165000
1%
15
b1 6
1*
0)
b0 7
#170000
0%
05
#175000
1%
15
b0 6
0*
1,
