Verilog/Session_3/Assignment_3/ALU_16B.v
module ALU_16B (

input wire [15:0] A,
input wire [15:0] B,
input wire [3:0]  ALU_FUN,
input wire        CLK,

output reg [15:0] ALU_OUT,
output reg        Carry_Flag,
output reg        Arith_flag,
output reg        Logic_flag,
output reg        CMP_flag,
output reg        Shift_flag );

//Internal connection
reg [15:0] ALU_OUT_Comb;

always @(posedge CLK ) 
    begin
        ALU_OUT <= ALU_OUT_Comb ; 
    end

always @(*) 
    begin
        // Ativating all the flags "LOW"
        Carry_Flag = 1'b0 ;
        Arith_flag = 1'b0 ;
        Logic_flag = 1'b0 ;
        CMP_flag = 1'b0 ;
        Shift_flag = 1'b0 ;
        
        case (ALU_FUN)
            4'b0000: //Arithmatic : unsigned Addition
                begin
                    {Carry_Flag,ALU_OUT_Comb} = A + B ;
                    Arith_flag = 1'b1;
                end

             4'b0001: //Arithmatic : unsigned Subtraction
                begin
                    ALU_OUT_Comb = A - B;
                    Carry_Flag = (A < B); // indicates borrow
                    Arith_flag = 1'b1;
                end 

             4'b0010: //Arithmatic : unsigned Multiplication
                begin
                    ALU_OUT_Comb = A * B ;
                    Arith_flag = 1'b1;
                end

             4'b0011: //Arithmatic : unsigned Division
                begin
                    Arith_flag = 1'b1;
                    if (B != 0) // check to avoid dividing by zero 
                        begin
                            ALU_OUT_Comb = A / B ;
                        end
                    else 
                        begin
                           ALU_OUT_Comb = 16'hFFFF; // ERROR 
                        end
                end 

            4'b0100: //Logic : AND
                begin
                    ALU_OUT_Comb = A & B ;
                    Logic_flag = 1'b1;
                end 

            4'b0101: //Logic : OR
                begin
                    ALU_OUT_Comb = A | B ;
                    Logic_flag = 1'b1;
                end 

            4'b0110: //Logic : NAND
                begin
                    ALU_OUT_Comb = ~(A & B) ;
                    Logic_flag = 1'b1;
                end 

            4'b0111: //Logic : NOR
                begin
                    ALU_OUT_Comb = ~(A | B) ;
                    Logic_flag = 1'b1;
                end 

            4'b1000: //Logic : XOR
                begin
                    ALU_OUT_Comb = A ^ B ;
                    Logic_flag = 1'b1;
                end 

            4'b1001: //Logic : XNOR
                begin
                    ALU_OUT_Comb = ~(A ^ B) ;
                    Logic_flag = 1'b1;
                end 

            4'b1010: //CMP: A = B
                begin
                    CMP_flag =1'b1;
                    if (A == B) 
                        begin
                            ALU_OUT_Comb = 16'h1;
                        end
                    else
                        begin
                            ALU_OUT_Comb = 16'h0;    
                        end
                end

            4'b1011: //CMP: A > B
                begin
                    CMP_flag =1'b1;
                    if (A > B) 
                        begin
                            ALU_OUT_Comb = 16'h2;
                        end
                    else
                        begin
                            ALU_OUT_Comb = 16'h0;    
                        end
                end
            
             4'b1100: //CMP: A < B
                begin
                    CMP_flag =1'b1;
                    if (A < B) 
                        begin
                            ALU_OUT_Comb = 16'h3;
                        end
                    else
                        begin
                            ALU_OUT_Comb = 16'h0;    
                        end
                end
            
            4'b1101: //SHIFT: A >> 1
                begin
                    ALU_OUT_Comb = A >> 1;
                    Shift_flag = 1'b1;
                end
            
            4'b1110: //SHIFT: A << 1
                begin
                    ALU_OUT_Comb = A << 1;
                    Shift_flag = 1'b1;
                end

            default: //For the case 1111 (the result is zero)
                begin
                    ALU_OUT_Comb = 16'b0;
                    Shift_flag = 1'b1;
                end 
        endcase    

    end

endmodule

Verilog/Session_3/Assignment_3/ALU_16B_tb.v
//time_unit = 1us & time percision = 1ns
`timescale 1us/1ns 

module ALU_16B_tb ();

reg [15:0] A_tb;
reg [15:0] B_tb;
reg [3:0]  ALU_FUN_tb;
reg        CLK_tb;

wire [15:0] ALU_OUT_tb;
wire        Carry_Flag_tb;
wire        Arith_flag_tb;
wire        Logic_flag_tb;
wire        CMP_flag_tb;
wire        Shift_flag_tb; 


initial 
    begin
        $dumpfile("ALU_16B.vcd");
		$dumpvars;

        CLK_tb = 1'b0;
        A_tb = 16'h0;
        B_tb = 16'h0;
        ALU_FUN_tb = 4'h0;
        
    //test cases
    //wait for one clk cycle
    	#10 
    $display("Add Test Case"); // test Add function
    A_tb = 16'd10;
    B_tb = 16'd20;
    ALU_FUN_tb = 4'b0000;
    #10
    if (ALU_OUT_tb == 16'd30 && Arith_flag_tb == 1'b1) 
        $display("Addition test case Passed with result = %0d at simulation time %0t", ALU_OUT_tb, $time);
    else 
        $display("Addition test case Failed with result = %0d at simulation time %0t", ALU_OUT_tb, $time);

    #10 
    $display("Overflow Test Case - ADD with Carry"); // Test carry flag
    A_tb = 16'hFFFF;     // 65535
    B_tb = 16'd1;        // +1
    ALU_FUN_tb = 4'b0000; 
    #10
    if (Carry_Flag_tb == 1'b1 && ALU_OUT_tb == 16'd0)
        $display("Carry Flag test Passed! Result = %0d, Carry = %b at time %t", ALU_OUT_tb, Carry_Flag_tb, $time);
    else
    $display("Carry Flag test Failed! Result = %0d, Carry = %b at time %t", ALU_OUT_tb, Carry_Flag_tb, $time);

    #10 
    $display("Subtract Test Case"); // test Subtraction
    A_tb = 16'd15;
    B_tb = 16'd10;
    ALU_FUN_tb = 4'b0001;
    #10
    if (ALU_OUT_tb == 16'd5 && Arith_flag_tb == 1'b1) 
        $display("Subtraction test case Passed with result = %0d at simulation time %0t", ALU_OUT_tb, $time);
    else 
        $display("Subtraction test case Failed with result = %0d at simulation time %0t", ALU_OUT_tb, $time);

    #10 
    $display("Multiply Test Case"); // test Multiplication
    A_tb = 16'd4;
    B_tb = 16'd5;
    ALU_FUN_tb = 4'b0010;
    #10
    if (ALU_OUT_tb == 16'd20 && Arith_flag_tb == 1'b1) 
        $display("Multiplication test case Passed with result = %0d at simulation time %0t", ALU_OUT_tb, $time);
    else 
        $display("Multiplication test case Failed with result = %0d at simulation time %0t", ALU_OUT_tb, $time);

    #10 
    $display("Divide Test Case"); // test Division
    A_tb = 16'd20;
    B_tb = 16'd4;
    ALU_FUN_tb = 4'b0011;
    #10
    if (ALU_OUT_tb == 16'd5 && Arith_flag_tb == 1'b1) 
        $display("Division test case Passed with result = %0d at simulation time %0t", ALU_OUT_tb, $time);
    else 
        $display("Division test case Failed with result = %0d at simulation time %0t", ALU_OUT_tb, $time);

    #10 
    $display("Division by Zero Test Case"); // Test div by zero
    A_tb = 16'd100;
    B_tb = 16'd0;
    ALU_FUN_tb = 4'b0011; // Assuming 0110 is division
    #10
    if (ALU_OUT_tb == 16'hFFFF) // FFFF = ERROR
        $display("Division by Zero handled gracefully. Result = %0h at time %t", ALU_OUT_tb, $time);
    else
        $display("Division by Zero test Failed. Unexpected result = %0d at time %t", ALU_OUT_tb, $time);

    #10 
    $display("And Test Case"); // test AND
    A_tb = 16'b1010101010101010;
    B_tb = 16'b1111000011110000;
    ALU_FUN_tb = 4'b0100;
    #10
    if ((ALU_OUT_tb == (A_tb & B_tb)) && (Logic_flag_tb == 1'b1)) 
        $display("AND test case Passed with result = %0b at simulation time %0t", ALU_OUT_tb, $time);
    else 
        $display("AND test case Failed with result = %0b at simulation time %0t", ALU_OUT_tb, $time);

    #10 
    $display("OR Test Case"); // test OR
    A_tb = 16'b0000111100001111;
    B_tb = 16'b1111000011110000;
    ALU_FUN_tb = 4'b0101;
    #10
    if ((ALU_OUT_tb == (A_tb | B_tb)) && (Logic_flag_tb == 1'b1)) 
        $display("OR test case Passed with result = %0b at simulation time %0t", ALU_OUT_tb, $time);
    else 
        $display("OR test case Failed with result = %0b at simulation time %0t", ALU_OUT_tb, $time);

    #10 
    $display("NAND Test Case"); // test NAND
    A_tb = 16'hFFFF;
    B_tb = 16'h0F0F;
    ALU_FUN_tb = 4'b0110;
    #10
    if ((ALU_OUT_tb == ~(A_tb & B_tb)) && (Logic_flag_tb == 1'b1)) 
        $display("NAND test case Passed with result = %0b at simulation time %0t", ALU_OUT_tb, $time);
    else 
        $display("NAND test case Failed with result = %0b at simulation time %0t", ALU_OUT_tb, $time);

    #10 
    $display("NOR Test Case"); // test NOR
    A_tb = 16'h0F0F;
    B_tb = 16'hF0F0;
    ALU_FUN_tb = 4'b0111;
    #10
    if ((ALU_OUT_tb == ~(A_tb | B_tb)) && (Logic_flag_tb == 1'b1)) 
        $display("NOR test case Passed with result = %0b at simulation time %0t", ALU_OUT_tb, $time);
    else 
        $display("NOR test case Failed with result = %0b at simulation time %0t", ALU_OUT_tb, $time);

    #10 
    $display("XOR Test Case"); // test XOR
    A_tb = 16'hAAAA;
    B_tb = 16'h5555;
    ALU_FUN_tb = 4'b1000;
    #10
    if ((ALU_OUT_tb == (A_tb ^ B_tb)) && (Logic_flag_tb == 1'b1)) 
        $display("XOR test case Passed with result = %0b at simulation time %0t", ALU_OUT_tb, $time);
    else 
        $display("XOR test case Failed with result = %0b at simulation time %0t", ALU_OUT_tb, $time);

    #10 
    $display("XNOR Test Case"); // test XNOR
    A_tb = 16'hAAAA;
    B_tb = 16'h5555;
    ALU_FUN_tb = 4'b1001;
    #10
    if ((ALU_OUT_tb == ~(A_tb ^ B_tb)) && (Logic_flag_tb == 1'b1)) 
        $display("XNOR test case Passed with result = %0b at simulation time %0t", ALU_OUT_tb, $time);
    else 
        $display("XNOR test case Failed with result = %0b at simulation time %0t", ALU_OUT_tb, $time);

    #10 
    $display("Equal Test Case"); // A == B
    A_tb = 16'd50;
    B_tb = 16'd50;
    ALU_FUN_tb = 4'b1010;
    #10
    if ((ALU_OUT_tb == 16'd1) && (CMP_flag_tb == 1'b1)) 
        $display("A == B test case Passed at simulation time %0t", $time);
    else 
        $display("A == B test case Failed at simulation time %0t", $time);

    #10 
    $display("Not Equal Test Case"); // A != B
    A_tb = 16'd50;
    B_tb = 16'd55;
    ALU_FUN_tb = 4'b1010;
    #10
    if ((ALU_OUT_tb == 16'd0) && (CMP_flag_tb == 1'b1)) 
        $display("A != B test case Passed at simulation time %0t", $time);
    else 
        $display("A != B test case Failed at simulation time %0t", $time);

    #10 
    $display("Greater than Test Case"); // A > B
    A_tb = 16'd60;
    B_tb = 16'd40;
    ALU_FUN_tb = 4'b1011;
    #10
    if ((ALU_OUT_tb == 16'd2) && (CMP_flag_tb == 1'b1)) 
        $display("A > B test case Passed at simulation time %0t", $time);
    else 
        $display("A > B test case Failed at simulation time %0t", $time);

    #10 
    $display("Smaller than Test Case"); // A < B
    A_tb = 16'd30;
    B_tb = 16'd45;
    ALU_FUN_tb = 4'b1100;
    #10
    if ((ALU_OUT_tb == 16'd3) && (CMP_flag_tb == 1'b1)) 
        $display("A < B test case Passed at simulation time %0t", $time);
    else 
        $display("A < B test case Failed at simulation time %0t", $time);

    #10 
    $display("Shift Right Test Case"); // Shift Right
    A_tb = 16'b1000000000000000;
    B_tb = 16'd0;
    ALU_FUN_tb = 4'b1101;
    #10
    if ((ALU_OUT_tb == 16'b0100000000000000) && (Shift_flag_tb == 1'b1)) 
        $display("Shift Right test case Passed with result = %0b at simulation time %0t", ALU_OUT_tb, $time);
    else 
        $display("Shift Right test case Failed with result = %0b at simulation time %0t", ALU_OUT_tb, $time);

    #10 
    $display("Shift left Test Case"); // Shift Left
    A_tb = 16'b0000000000000001;
    B_tb = 16'd0;
    ALU_FUN_tb = 4'b1110;
    #10
    if ((ALU_OUT_tb == 16'b0000000000000010) && (Shift_flag_tb == 1'b1)) 
        $display("Shift Left test case Passed with result = %0b at simulation time %0t", ALU_OUT_tb, $time);
    else 
        $display("Shift Left test case Failed with result = %0b at simulation time %0t", ALU_OUT_tb, $time);

    #10 
    $display("NOP Test Case"); // Default (Zero Output)
    A_tb = 16'd123;
    B_tb = 16'd456;
    ALU_FUN_tb = 4'b1111;
    #10
    if (ALU_OUT_tb == 16'd0) 
        $display("Default test case Passed with result = %0d at simulation time %0t", ALU_OUT_tb, $time);
    else 
        $display("Default test case Failed with result = %0d at simulation time %0t", ALU_OUT_tb, $time);
    
    #100
    $stop; //finish simulation
    end






// Clock Generator (toogle each 5us to get 100KHz freqeuncy)
always#5 CLK_tb = ~CLK_tb ;

// Design inistantiation
ALU_16B DUt (

    .A(A_tb),
    .B(B_tb),
    .ALU_FUN(ALU_FUN_tb),
    .CLK(CLK_tb),
    .ALU_OUT(ALU_OUT_tb),
    .Carry_Flag(Carry_Flag_tb),
    .Arith_flag(Arith_flag_tb),
    .Logic_flag(Logic_flag_tb),
    .CMP_flag(CMP_flag_tb),
    .Shift_flag(Shift_flag_tb)
    );

endmodule

Verilog/Session_3/Assignment_3/ALU_16B.vcd
$date
	Thu Jul 17 11:43:30 2025
$end
$version
	QuestaSim Version 2021.1
$end
$timescale
	1ns
$end

$scope module ALU_16B_tb $end
$var reg 16 ! A_tb [15:0] $end
$var reg 16 " B_tb [15:0] $end
$var reg 4 # ALU_FUN_tb [3:0] $end
$var reg 1 $ CLK_tb $end
$var wire 1 % ALU_OUT_tb [15] $end
$var wire 1 & ALU_OUT_tb [14] $end
$var wire 1 ' ALU_OUT_tb [13] $end
$var wire 1 ( ALU_OUT_tb [12] $end
$var wire 1 ) ALU_OUT_tb [11] $end
$var wire 1 * ALU_OUT_tb [10] $end
$var wire 1 + ALU_OUT_tb [9] $end
$var wire 1 , ALU_OUT_tb [8] $end
$var wire 1 - ALU_OUT_tb [7] $end
$var wire 1 . ALU_OUT_tb [6] $end
$var wire 1 / ALU_OUT_tb [5] $end
$var wire 1 0 ALU_OUT_tb [4] $end
$var wire 1 1 ALU_OUT_tb [3] $end
$var wire 1 2 ALU_OUT_tb [2] $end
$var wire 1 3 ALU_OUT_tb [1] $end
$var wire 1 4 ALU_OUT_tb [0] $end
$var wire 1 5 Carry_Flag_tb $end
$var wire 1 6 Arith_flag_tb $end
$var wire 1 7 Logic_flag_tb $end
$var wire 1 8 CMP_flag_tb $end
$var wire 1 9 Shift_flag_tb $end

$scope module DUt $end
$var wire 1 : A [15] $end
$var wire 1 ; A [14] $end
$var wire 1 < A [13] $end
$var wire 1 = A [12] $end
$var wire 1 > A [11] $end
$var wire 1 ? A [10] $end
$var wire 1 @ A [9] $end
$var wire 1 A A [8] $end
$var wire 1 B A [7] $end
$var wire 1 C A [6] $end
$var wire 1 D A [5] $end
$var wire 1 E A [4] $end
$var wire 1 F A [3] $end
$var wire 1 G A [2] $end
$var wire 1 H A [1] $end
$var wire 1 I A [0] $end
$var wire 1 J B [15] $end
$var wire 1 K B [14] $end
$var wire 1 L B [13] $end
$var wire 1 M B [12] $end
$var wire 1 N B [11] $end
$var wire 1 O B [10] $end
$var wire 1 P B [9] $end
$var wire 1 Q B [8] $end
$var wire 1 R B [7] $end
$var wire 1 S B [6] $end
$var wire 1 T B [5] $end
$var wire 1 U B [4] $end
$var wire 1 V B [3] $end
$var wire 1 W B [2] $end
$var wire 1 X B [1] $end
$var wire 1 Y B [0] $end
$var wire 1 Z ALU_FUN [3] $end
$var wire 1 [ ALU_FUN [2] $end
$var wire 1 \ ALU_FUN [1] $end
$var wire 1 ] ALU_FUN [0] $end
$var wire 1 ^ CLK $end
$var reg 16 _ ALU_OUT [15:0] $end
$var reg 1 ` Carry_Flag $end
$var reg 1 a Arith_flag $end
$var reg 1 b Logic_flag $end
$var reg 1 c CMP_flag $end
$var reg 1 d Shift_flag $end
$var reg 16 e ALU_OUT_Comb [15:0] $end
$upscope $end
$upscope $end
$enddefinitions $end
#0
$dumpvars
b0 !
b0 "
b0 #
0$
bx _
0`
1a
0b
0c
0d
b0 e
x4
x3
x2
x1
x0
x/
x.
x-
x,
x+
x*
x)
x(
x'
x&
x%
05
16
07
08
09
0^
0]
0\
0[
0Z
0Y
0X
0W
0V
0U
0T
0S
0R
0Q
0P
0O
0N
0M
0L
0K
0J
0I
0H
0G
0F
0E
0D
0C
0B
0A
0@
0?
0>
0=
0<
0;
0:
$end
#5000
1$
1^
b0 _
04
03
02
01
00
0/
0.
0-
0,
0+
0*
0)
0(
0'
0&
0%
#10000
b1010 !
b10100 "
0$
1W
1U
1H
1F
0^
0a
b11110 e
1a
#15000
1$
1^
b11110 _
13
12
11
10
#20000
0$
0^
#25000
1$
1^
#30000
b1111111111111111 !
b1 "
0$
1Y
0W
0U
1I
1G
1E
1D
1C
1B
1A
1@
1?
1>
1=
1<
1;
1:
0^
0a
b0 e
1`
1a
15
#35000
1$
1^
b0 _
03
02
01
00
#40000
0$
0^
#45000
1$
1^
#50000
b1111 !
b1010 "
b1 #
0$
1]
0Y
1X
1V
0E
0D
0C
0B
0A
0@
0?
0>
0=
0<
0;
0:
0^
0`
0a
b101 e
1a
05
#55000
1$
1^
b101 _
14
12
#60000
0$
0^
#65000
1$
1^
#70000
b100 !
b101 "
b10 #
0$
0]
1\
1Y
0X
1W
0V
0I
0H
0F
0^
0a
b10100 e
1a
#75000
1$
1^
b10100 _
04
10
#80000
0$
0^
#85000
1$
1^
#90000
b10100 !
b100 "
b11 #
0$
1]
0Y
1E
0^
0a
1a
b101 e
#95000
1$
1^
b101 _
14
00
#100000
0$
0^
#105000
1$
1^
#110000
b1100100 !
b0 "
0$
0W
0E
1D
1C
0^
0a
1a
b1111111111111111 e
#115000
1$
1^
b1111111111111111 _
13
11
10
1/
1.
1-
1,
1+
1*
1)
1(
1'
1&
1%
#120000
0$
0^
#125000
1$
1^
#130000
b1010101010101010 !
b1111000011110000 "
b100 #
0$
0]
0\
1[
1U
1T
1S
1R
1M
1L
1K
1J
1H
0G
1F
0C
1B
1@
1>
1<
1:
0^
0a
b1010000010100000 e
1b
06
17
#135000
1$
1^
b1010000010100000 _
04
03
02
01
00
0.
0,
0+
0*
0)
0(
0&
#140000
0$
0^
#145000
1$
1^
#150000
b111100001111 !
b101 #
0$
1]
1I
1G
0D
0B
1A
1?
0<
0:
0^
0b
b1111111111111111 e
1b
#155000
1$
1^
b1111111111111111 _
14
13
12
11
10
1.
1,
1+
1*
1)
1(
1&
#160000
0$
0^
#165000
1$
1^
#170000
b1111111111111111 !
b111100001111 "
b110 #
0$
0]
1\
1Y
1X
1W
1V
0U
0T
0S
0R
1Q
1P
1O
1N
0M
0L
0K
0J
1E
1D
1C
1B
1=
1<
1;
1:
0^
0b
b1111000011110000 e
1b
#175000
1$
1^
b1111000011110000 _
04
03
02
01
0,
0+
0*
0)
#180000
0$
0^
#185000
1$
1^
#190000
b111100001111 !
b1111000011110000 "
b111 #
0$
1]
0Y
0X
0W
0V
1U
1T
1S
1R
0Q
0P
0O
0N
1M
1L
1K
1J
0E
0D
0C
0B
0=
0<
0;
0:
0^
0b
b0 e
1b
#195000
1$
1^
b0 _
00
0/
0.
0-
0(
0'
0&
0%
#200000
0$
0^
#205000
1$
1^
#210000
b1010101010101010 !
b101010101010101 "
b1000 #
0$
0]
0\
0[
1Z
1Y
1W
0T
0R
1Q
1O
0L
0J
0I
0G
1D
1B
0A
0?
1<
1:
0^
0b
b1111111111111111 e
1b
#215000
1$
1^
b1111111111111111 _
14
13
12
11
10
1/
1.
1-
1,
1+
1*
1)
1(
1'
1&
1%
#220000
0$
0^
#225000
1$
1^
#230000
b1001 #
0$
1]
0^
0b
b0 e
1b
#235000
1$
1^
b0 _
04
03
02
01
00
0/
0.
0-
0,
0+
0*
0)
0(
0'
0&
0%
#240000
0$
0^
#245000
1$
1^
#250000
b110010 !
b110010 "
b1010 #
0$
0]
1\
0Y
1X
0W
1T
0S
0Q
0O
0M
0K
0F
1E
0B
0@
0>
0<
0:
0^
0b
1c
b1 e
07
18
#255000
1$
1^
b1 _
14
#260000
0$
0^
#265000
1$
1^
#270000
b110111 "
0$
1Y
1W
0^
0c
1c
b0 e
#275000
1$
1^
b0 _
04
#280000
0$
0^
#285000
1$
1^
#290000
b111100 !
b101000 "
b1011 #
0$
1]
0Y
0X
0W
1V
0U
0H
1G
1F
0^
0c
1c
b10 e
#295000
1$
1^
b10 _
13
#300000
0$
0^
#305000
1$
1^
#310000
b11110 !
b101101 "
b1100 #
0$
0]
0\
1[
1Y
1W
1H
0D
0^
0c
1c
b11 e
#315000
1$
1^
b11 _
14
#320000
0$
0^
#325000
1$
1^
#330000
b1000000000000000 !
b0 "
b1101 #
0$
1]
0Y
0W
0V
0T
0H
0G
0F
0E
1:
0^
0c
b100000000000000 e
1d
08
19
#335000
1$
1^
b100000000000000 _
04
03
1&
#340000
0$
0^
#345000
1$
1^
#350000
b1 !
b1110 #
0$
0]
1\
1I
0:
0^
0d
b10 e
1d
#355000
1$
1^
b10 _
13
0&
#360000
0$
0^
#365000
1$
1^
#370000
b1111011 !
b111001000 "
b1111 #
0$
1]
1V
1S
1R
1Q
1H
1F
1E
1D
1C
0^
0d
b0 e
1d
#375000
1$
1^
b0 _
03
